ALU.v
`timescale 1ns / 1ps

/*
ALU Module

Performs arithmetic operations for add,
sub, and, or operations. Also performs 
comparison operation for beq, blt.
*/

module ALU(
    input wire [31:0] ip_0,
    input wire [31:0] ip_1,
    input wire [2:0] opcode,
    output wire [31:0] op_0,
    output wire change_pc
    );
    
    // Use assign statement to perform add, sub,
    // and, or operations on ip_0 and ip_1 based 
    // on the instruction/opcode
    
    assign op_0 = 
    
    
    // Change_pc is required for the branch operations for 
    // the two control instructions. If ip_0 and ip_1 are equal 
    //  when the instruction is "beq" or ip_0 < ip_1 when 
    // instruction is "blt", the change_pc goes high 
    
    assign change_pc = opcode == 2 ? (ip_0 == ip_1):(
                        opcode == 3 ? (ip_0 < ip_1) : 0);
    
    
endmodule

RegisterFile.v
`timescale 1ns / 1ps

/*
RegisterFile Module

A 2-d register array with two read ports
and one write port
*/


module  RegisterFile(
    input [4:0] read_address_0,
    input [4:0] read_address_1,
    input [4:0] write_address_0,
    input write_en,
    input [31:0] write_data,
    output [31:0] read_data_0,
    output [31:0] read_data_1
    );
    
    reg [31:0] ram [255:0];
    integer i;
    
    // Initialize the entire ram to zero
    initial begin
        for(i=0; i<256; i=i+1) begin
            ram[i] = '0 ;
        end
    end

// Use assign statment to read data from ram 
// based on read_address_1 and assign it to 
// read_data_1. See example below   

    assign read_data_0 = ram[read_address_0];
    assign read_data_1 = ram[read_address_1];
    
    always @* begin
        if(write_en) begin
			            // When write_en is high write the write_data 
       			            // to the ram based on address write_address_0 
        end
    end
    
endmodule

DataMemory.v
`timescale 1ns / 1ps

/*
DataMemory Module

A 2-d register array with one read ports
and one write port
*/

module  DataMemory(
    input [14:0] data_address,
    input write_en,
    input [31:0] write_data,
    output [31:0] read_data
    );
    integer i;
    reg [31:0] ram [255:0];
    
    // Use a for loop to initialize each block in ram 
    // to its index. For example ram[0], ram[1], ram[2]
    // contains 0, 1, 2 respectively. 
    initial begin
	for(int i = 0 ; i < 2 ; i++) begin
		ram[i] <= i ; 	
	end
    end
    
    
    // Use assign statement to read ram based on 
    // data_address and drive the read_data output
    
    always @* begin
        if(write_en) begin
            // When write_en is high write the write_data 
            // to the ram based on address write_address_0 
        end
    end
    
endmodule

InstructionMemory.v
`timescale 1ns / 1ps
/*
Instruction Module

A 2-d register array with one read port
*/








// I believe this is done


module  InstructionMemory(
    input [15:0] inst_address,
    output [31:0] read_data
    );
    
    reg [31:0] ram [255:0];

    // Initialize Instructions in the memory for testing
    initial begin
        ram[0] <= 32'h2000_0004; // Store instruction that reads registerFile[0] and write to dataMemory[4].
    end
    
    reg [31:0] ram [255:0];
    
    // Assign statement to read ram based on inst_address
    assign read_data = ram[inst_address] ; 

  
endmodule

Decoder.v
`timescale 1ns / 1ps
/*
Decoder Module

Takes a 32-bit instruction as input and drives each
of the output based on the Instruction Set Architecture
given in the project instructions
*/


module  Decoder(
    input [31:0] inst, 
    output [2:0] opcode,
    output [4:0] reg_addr_0,
    output [4:0] reg_addr_1,
    output [4:0] reg_addr_2,
    output [14:0] addr
    );
    
    // Use assign statements to redirect parts of the instruction to output
    assign opcode = inst[31:29];
    assign addr =
    assign reg_addr_0 =
    assign reg_addr_1 =
    assign reg_addr_2 =
    
endmodule

CPU.v
`timescale 1ns / 1ps

/*
CPU Module

Top Module for CPU.

*/

`include "Decoder.v"
`include "ALU.v"
`include "InstructionMemory.v"
`include "DataMemory.v"
`include "RegisterFile.v"


module CPU( input clk
    );
    
     
    reg [15:0]  pc_q = 0;      // Program Counter
    reg [31:0]  instruction_q; // Holds instruction binary 
    reg [1:0]   state_q = 0;   // State of CPU
    
    // Instantiate decoder, Instruction Memory,
    // Data Memory, Register File and ALU
   Decoder u_decoder (.inst(inst));
   InstructionMemory u_InstructionMemory ();
   DataMemory u_DataMemory ();
   RegisterFile u_RegisterFile();
   ALU u_ALU(); 
    
   reg [2:0] opcode ; 
   reg [4:0] reg_addr_0 ; 
   reg [4:0] reg_addr_1 ; 
   reg [4:0] reg_addr_2 ; 
   reg [15:0] addr ;  
   reg [31:0] inst ; 

     
    always@(posedge clk)
    begin
        if(state_q == 0) begin // Fetch Stage
         instruction_q =  u_InstructionMemory.read_data ;   		 // Read instruction from instruction memory
         pc_q <=  pc_q + 1'b1 ; 						 // increment PC
         state_q <= 2'b1 ; 					   	         // increment state
        end else if(state_q == 1) begin  // Decode Stage       
            inst = instruction_q ; 			// Instruction Decode and read data from register/memory
            opcode <= u_decoder.opcode ;			// store all data necessary for next stages in a register
	    reg_addr_0 <=u_decoder.reg_addr_0 ; 
	    reg_addr_1 <=u_decoder.reg_addr_1 ; 
	    reg_addr_2 <=u_decoder.reg_addr_2 ; 
	    addr       <=u_decoder.addr	      ; 
	     
            state_q <= 2;  //update state
        end else if(state_q == 2) begin  // Execute Stage        
            // Perform ALU operations
	    
            state_q <= 3; //update state
        end else if(state_q == 3) begin  // Memory Stage
            // Access Memory and register file(for load)
            state_q <= 0;
        end    
    end
    
endmodule

sim.sv
`timescale 1ns / 1ps
`include "CPU.v"
module tb_top();
 
 logic  clk = 0  ; 

 CPU u_CPU  (.clk (clk));

 always #1 clk = ~clk ; 


 initial begin
   $dumpfile("dump.vcd"); 
   $dumpvars(0, tb_top);
   repeat(1000) begin
   u_CPU.instruction_q = $urandom; 
   #1 ; 
   end


  $finish;
 end



endmodule

dump.vcd
$date
	Tue Apr 16 21:15:45 2024
$end
$version
	Icarus Verilog
$end
$timescale
	1ps
$end
$scope module tb_top $end
$var reg 1 ! clk $end
$scope module u_CPU $end
$var wire 1 ! clk $end
$var reg 16 " addr [15:0] $end
$var reg 32 # inst [31:0] $end
$var reg 32 $ instruction_q [31:0] $end
$var reg 3 % opcode [2:0] $end
$var reg 16 & pc_q [15:0] $end
$var reg 5 ' reg_addr_0 [4:0] $end
$var reg 5 ( reg_addr_1 [4:0] $end
$var reg 5 ) reg_addr_2 [4:0] $end
$var reg 2 * state_q [1:0] $end
$scope module u_ALU $end
$var wire 32 + ip_0 [31:0] $end
$var wire 32 , ip_1 [31:0] $end
$var wire 3 - opcode [2:0] $end
$var wire 32 . op_0 [31:0] $end
$var wire 1 / change_pc $end
$upscope $end
$scope module u_DataMemory $end
$var wire 15 0 data_address [14:0] $end
$var wire 32 1 read_data [31:0] $end
$var wire 32 2 write_data [31:0] $end
$var wire 1 3 write_en $end
$var integer 32 4 i [31:0] $end
$upscope $end
$scope module u_InstructionMemory $end
$var wire 16 5 inst_address [15:0] $end
$var wire 32 6 read_data [31:0] $end
$upscope $end
$scope module u_RegisterFile $end
$var wire 5 7 read_address_0 [4:0] $end
$var wire 5 8 read_address_1 [4:0] $end
$var wire 32 9 read_data_0 [31:0] $end
$var wire 32 : read_data_1 [31:0] $end
$var wire 5 ; write_address_0 [4:0] $end
$var wire 32 < write_data [31:0] $end
$var wire 1 = write_en $end
$var integer 32 > i [31:0] $end
$upscope $end
$scope module u_decoder $end
$var wire 32 ? inst [31:0] $end
$var wire 5 @ reg_addr_2 [4:0] $end
$var wire 5 A reg_addr_1 [4:0] $end
$var wire 5 B reg_addr_0 [4:0] $end
$var wire 3 C opcode [2:0] $end
$var wire 15 D addr [14:0] $end
$upscope $end
$upscope $end
$upscope $end
$enddefinitions $end
#0
$dumpvars
bx D
bx C
bx B
bx A
b0xxx @
bx ?
b100000000 >
z=
bz <
bz ;
bx :
bx 9
bz 8
bz 7
bx 6
bz 5
b100000000 4
z3
bz 2
bz 1
bz 0
x/
bx .
bz -
bz ,
bz +
b0 *
bx )
bx (
bx '
b0 &
bx %
b10010010000101010011010100100100 $
bx #
bx "
0!
$end
#1000
b1 *
b1 &
bx $
1!
#2000
b100100001001101011000001001 $
0!
#3000
b10 *
b0xxxxxxxxxxxxxxx "
b0xxx )
b101011001100011 D
b1 C
b10001 B
b11110 A
b0 @
b110001111100000101011001100011 #
b110001111100000101011001100011 ?
b110001111100000101011001100011 $
1!
#4000
b10000110101110010111101100001101 $
0!
#5000
b11 *
b11000110110111111001100110001101 $
1!
#6000
b110010110000101000010001100101 $
0!
#7000
b0 *
b1001001101110101001000010010 $
1!
#8000
b10000000111100111110001100000001 $
0!
#9000
b1 *
b10 &
bx $
1!
#10000
b10111011001000111111000101110110 $
0!
#11000
b10 *
b101011001100011 "
b0 )
b11110 (
b10001 '
b1 %
b100110100111101 D
b100 C
b11110 B
b10001 A
b101 @
b10011110100011011100110100111101 #
b10011110100011011100110100111101 ?
b10011110100011011100110100111101 $
1!
#12000
b11110110110101000101011111101101 $
0!
#13000
b11 *
b11000110001011011111011110001100 $
1!
#14000
b11111100111111011110100111111001 $
0!
#15000
b0 *
b1100011001101110010010011000110 $
1!
#16000
b1100010111101111000010011000101 $
0!
#17000
b1 *
b11 &
bx $
1!
#18000
b11110010101011111111011111100101 $
0!
#19000
b10 *
b100110100111101 "
b101 )
b10001 (
b11110 '
b100 %
b111001001110111 D
b1 C
b11011 B
b11010 A
b10 @
b111011110100100111001001110111 #
b111011110100100111001001110111 ?
b111011110100100111001001110111 $
1!
#20000
b1001001100101101011000010010 $
0!
#21000
b11 *
b11000111111011001101101110001111 $
1!
#22000
b11111001001100000110100111110010 $
0!
#23000
b0 *
b1100111011101101001011011001110 $
1!
#24000
b1110100000000000111101011101000 $
0!
#25000
b1 *
b100 &
bx $
1!
#26000
b10101110010110000100100101011100 $
0!
#27000
b10 *
b111001001110111 "
b10 )
b11010 (
b11011 '
b1 %
b10100010111101 D
b10 C
b11110 B
b10001 A
b110 @
b1011110100011100010100010111101 #
b1011110100011100010100010111101 ?
b1011110100011100010100010111101 $
1!
#28000
b10110101010110101100000101101 $
0!
#29000
b11 *
b110010101001110010011001100101 $
1!
#30000
b110001111011110110001001100011 $
0!
#31000
b0 *
b10000101011100111000011100001010 $
1!
#32000
b1000000001110110010001010000000 $
0!
#33000
b1 *
b101 &
bx $
1!
#34000
b11010101011110000100010110101010 $
0!
#35000
b10 *
b10100010111101 "
b110 )
b10001 (
b11110 '
b10 %
b100110010011101 D
b1110 B
b11001 A
b100 @
b1001110110011001100110010011101 #
b1001110110011001100110010011101 ?
b1001110110011001100110010011101 $
1!
#36000
b1001011001000000011111010010110 $
0!
#37000
b11 *
b1001100000111011100000010011 $
1!
#38000
b110101111000011100000001101 $
0!
#39000
b0 *
b101001101001111101011001010011 $
1!
#40000
b10110101100111111101110101101011 $
0!
#41000
b1 *
b110 &
bx $
1!
#42000
b1000101110100101000000010 $
0!
#43000
b10 *
b100110010011101 "
b100 )
b11001 (
b1110 '
b11111010101110 D
b10111 B
b1010 A
b110 @
b1010111010101100011111010101110 #
b1010111010101100011111010101110 ?
b1010111010101100011111010101110 $
1!
#44000
b10001110111111111110100100011101 $
0!
#45000
b11 *
b1100111110001010111001011001111 $
1!
#46000
b10010001100001000100100100100011 $
0!
#47000
b0 *
b10000101000010010110010100001010 $
1!
#48000
b1100101011100110000101011001010 $
0!
#49000
b1 *
b111 &
bx $
1!
#50000
b11111001011010001011110111110010 $
0!
#51000
b10 *
b11111010101110 "
b110 )
b1010 (
b10111 '
b110000110001010 D
b110 C
b101 B
b101 A
b11000101001011100110000110001010 #
b11000101001011100110000110001010 ?
b11000101001011100110000110001010 $
1!
#52000
b10100000110001001011001101000001 $
0!
#53000
b11 *
b1101100010010110011010011011000 $
1!
#54000
b10111100001000001111001101111000 $
0!
#55000
b0 *
b1000100100010100001001010001001 $
1!
#56000
b11110101110001010000110111101011 $
0!
#57000
b1 *
b1000 &
bx $
1!
#58000
b11100011010010111111100111000110 $
0!
#59000
b10 *
b110000110001010 "
b101 (
b101 '
b110 %
b1001110101110 D
b10111 B
b10 A
b101 @
b11010111000101010001001110101110 #
b11010111000101010001001110101110 ?
b11010111000101010001001110101110 $
1!
#60000
b1011110011101010000001010111100 $
0!
#61000
b11 *
b10010101000011111101110100101010 $
1!
#62000
b101110101111001101000001011 $
0!
#63000
b0 *
b111000100101111011111001110001 $
1!
#64000
b11000010111100100100000110000101 $
0!
#65000
b1 *
b1001 &
bx $
1!
#66000
b11101110011000110000000111011 $
0!
#67000
b10 *
b1001110101110 "
b101 )
b10 (
b10111 '
b11001100111010 D
b100 C
b11101 B
b0 A
b110 @
b10011101000001100011001100111010 #
b10011101000001100011001100111010 ?
b10011101000001100011001100111010 $
1!
#68000
b111111001000110011001001111110 $
0!
#69000
b11 *
b10001010101010100100101100010101 $
1!
#70000
b11111000110110011001101111110001 $
0!
#71000
b0 *
b11101100100111000100101111011001 $
1!
#72000
b10110001001000110000011101100010 $
0!
#73000
b1 *
b1010 &
bx $
1!
#74000
b11001111101000010101010110011111 $
0!
#75000
b10 *
b11001100111010 "
b110 )
b0 (
b11101 '
b100 %
b10000110001111 D
b110 C
b111 B
b10111 A
b1 @
b11000111101110011010000110001111 #
b11000111101110011010000110001111 ?
b11000111101110011010000110001111 $
1!
#76000
b11111100011011011010100111111000 $
0!
#77000
b11 *
b1011011110011010110000010110111 $
1!
#78000
b1001111110001000101011010011111 $
0!
#79000
b0 *
b101110011111011001010001011100 $
1!
#80000
b101101110010111100000001011011 $
0!
#81000
b1 *
b1011 &
bx $
1!
#82000
b100100101011100011001001001001 $
0!
#83000
b10 *
b10000110001111 "
b1 )
b10111 (
b111 '
b110 %
b11111011010000 D
b11 C
b1000 B
b100 A
b11 @
b1101000001000110011111011010000 #
b1101000001000110011111011010000 ?
b1101000001000110011111011010000 $
1!
#84000
b1101011111111101100000011010111 $
0!
#85000
b11 *
b101000110001111111110001010001 $
1!
#86000
b11001011001000010010111110010110 $
0!
#87000
b0 *
b10000110000111010111111100001100 $
1!
#88000
b1100001001011001100111011000010 $
0!
#89000
b1 *
b1100 &
bx $
1!
#90000
b111011100000100101101001110111 $
0!
#91000
b10 *
b11111011010000 "
b11 )
b100 (
b1000 '
b11 %
b110110100111101 D
b100 C
b11110 B
b11110 A
b10 @
b10011110111100101110110100111101 #
b10011110111100101110110100111101 ?
b10011110111100101110110100111101 $
1!
#92000
b10001001000011001101101100010010 $
0!
#93000
b11 *
b111111000001010000000001111110 $
1!
#94000
b10110110111001011000000101101101 $
0!
#95000
b0 *
b10011100110110011110011100111001 $
1!
#96000
b10001111110100101000111100011111 $
0!
#97000
b1 *
b1101 &
bx $
1!
#98000
b11000010110110010010111110000101 $
0!
#99000
b10 *
b110110100111101 "
b10 )
b11110 (
b11110 '
b100 %
b100001111000 D
b1 C
b11100 B
b10 A
b100 @
b111100000101001000100001111000 #
b111100000101001000100001111000 ?
b111100000101001000100001111000 $
1!
#100000
b10101101110110100101100101011011 $
0!
#101000
b11 *
b10100100100010110100101101001001 $
1!
#102000
b11111111100101010111000111111 $
0!
#103000
b0 *
b10010101000011001010111100101010 $
1!
#104000
b10101100000101010110001101011000 $
0!
#105000
b1 *
b1110 &
bx $
1!
#106000
b1000111000110100000110010001110 $
0!
#107000
b10 *
b100001111000 "
b100 )
b10 (
b11100 '
b1 %
b111001010011100 D
b10 C
b1110 B
b101 A
b111 @
b1001110001011111111001010011100 #
b1001110001011111111001010011100 ?
b1001110001011111111001010011100 $
1!
#108000
b11111101001101011001100111111010 $
0!
#109000
b11 *
b10011011111011011110000100110 $
1!
#110000
b10111001100101100001011101110011 $
0!
#111000
b0 *
b1010001100010111011010010100011 $
1!
#112000
b10111100110011010100000101111 $
0!
#113000
b1 *
b1111 &
bx $
1!
#114000
b101111110110000101011001011111 $
0!
#115000
b10 *
b111001010011100 "
b111 )
b101 (
b1110 '
b10 %
b110101000100 D
b101 C
b10 B
b1 @
b10100010001010010000110101000100 #
b10100010001010010000110101000100 ?
b10100010001010010000110101000100 $
1!
#116000
b11111011111110001111110111110111 $
0!
#117000
b11 *
b1100101100110110011011011001011 $
1!
#118000
b1110011000010010001101011100110 $
0!
#119000
b0 *
b10101101001010001101101101011010 $
1!
#120000
b10010100110011111100000100101001 $
0!
#121000
b1 *
b10000 &
bx $
1!
#122000
b1101101010100110110110011011010 $
0!
#123000
b10 *
b110101000100 "
b1 )
b10 '
b101 %
b11011001100101 D
b1 C
b10010 B
b10011 A
b111 @
b110010100111111011011001100101 #
b110010100111111011011001100101 ?
b110010100111111011011001100101 $
1!
#124000
b1011010100010101110001010110101 $
0!
#125000
b11 *
b1101111101111101001010011011111 $
1!
#126000
b10111100111100010001100101111001 $
0!
#127000
b0 *
b10100010001100011111111101000100 $
1!
#128000
b1101000011101000000110011010000 $
0!
#129000
b1 *
b10001 &
bx $
1!
#130000
b11010101111101101010110110101011 $
0!
#131000
b10 *
b11011001100101 "
b111 )
b10011 (
b10010 '
b1 %
b100111100001110 D
b100 C
b111 B
b1101 A
b10000111011011111100111100001110 #
b10000111011011111100111100001110 ?
b10000111011011111100111100001110 $
1!
#132000
b11101110010111011010110111011100 $
0!
#133000
b11 *
b1001101010111101011110010011010 $
1!
#134000
b1111110110111110111001011111101 $
0!
#135000
b0 *
b1100001111100010000001011000011 $
1!
#136000
b10101011000011101110110101010110 $
0!
#137000
b1 *
b10010 &
bx $
1!
#138000
b110011110110010111011001100111 $
0!
#139000
b10 *
b100111100001110 "
b1101 (
b111 '
b100 %
b11010000001010 D
b0 C
b101 B
b110 A
b1 @
b101001100010011010000001010 #
b101001100010011010000001010 ?
b101001100010011010000001010 $
1!
#140000
b11011011011011111011100110110110 $
0!
#141000
b11 *
b11100000011101000101000111000 $
1!
#142000
b10111100110100011000011101111001 $
0!
#143000
b0 *
b1011100001010111100010010111000 $
1!
#144000
b11001010011101001011111110010100 $
0!
#145000
b1 *
b10011 &
bx $
1!
#146000
b10001111110010110000000100 $
0!
#147000
b10 *
b11010000001010 "
b1 )
b110 (
b101 '
b0 %
b100101001011001 D
b1 C
b1100 B
b10110 A
b111 @
b101100101101111100101001011001 #
b101100101101111100101001011001 ?
b101100101101111100101001011001 $
1!
#148000
b11101101110010110110100111011011 $
0!
#149000
b11 *
b100110111111001101111001001101 $
1!
#150000
b11101100101100001011011111011001 $
0!
#151000
b0 *
b110110101001000010011001101101 $
1!
#152000
b111011010001011110001001110110 $
0!
#153000
b1 *
b10100 &
bx $
1!
#154000
b11011011000101110010110110110110 $
0!
#155000
b10 *
b100101001011001 "
b111 )
b10110 (
b1100 '
b1 %
b111000110010101 D
b110 C
b1010 B
b10010 A
b11 @
b11001010100100110111000110010101 #
b11001010100100110111000110010101 ?
b11001010100100110111000110010101 $
1!
#156000
b100011000001110001101001000110 $
0!
#157000
b11 *
b10000010011101001001101100000100 $
1!
#158000
b11111011110100100110000111110111 $
0!
#159000
b0 *
b10110100100110000000011101101001 $
1!
#160000
b1011010011011101011101010110100 $
0!
#161000
b1 *
b10101 &
bx $
1!
#162000
b10010100011111001101100100101000 $
0!
#163000
b10 *
b111000110010101 "
b11 )
b10010 (
b1010 '
b110 %
b10000101101 D
b0 C
b10110 B
b0 @
b10110100100000000010000101101 #
b10110100100000000010000101101 ?
b10110100100000000010000101101 $
1!
#164000
b1100011110001010011000011000111 $
0!
#165000
b11 *
b10111010111001001110000101110 $
1!
#166000
b100011101111110010000001000 $
0!
#167000
b0 *
b10001110010000010100010100011100 $
1!
#168000
b1111110101001111010011011111101 $
0!
#169000
b1 *
b10110 &
bx $
1!
#170000
b1110001101111001000000011100 $
0!
#171000
b10 *
b10000101101 "
b0 )
b10110 '
b0 %
b110011110000110 D
b110 C
b11 B
b110 A
b101 @
b11000011001101010110011110000110 #
b11000011001101010110011110000110 ?
b11000011001101010110011110000110 $
1!
#172000
b1101101001101000000100011011010 $
0!
#173000
b11 *
b11110101101111100011000111101 $
1!
#174000
b10110011010011101010011101100110 $
0!
#175000
b0 *
b111000010101011100010001110000 $
1!
#176000
b111001111101010000010001110011 $
0!
#177000
b1 *
b10111 &
bx $
1!
#178000
b10101111001110101011001101011110 $
0!
#179000
b10 *
b110011110000110 "
b101 )
b110 (
b11 '
b110 %
b111100111111010 D
b111 C
b11101 B
b1000 A
b111 @
b11111101010001110111100111111010 #
b11111101010001110111100111111010 ?
b11111101010001110111100111111010 $
1!
#180000
b11101010100011100000010111010101 $
0!
#181000
b11 *
b1101001001001111011000011010 $
1!
#182000
b1011100111100000000000010111001 $
0!
#183000
b0 *
b10011011100001110110000100110111 $
1!
#184000
b11001011001001110011011110010110 $
0!
#185000
b1 *
b11000 &
bx $
1!
#186000
b10010011001001011001111100100110 $
0!
#187000
b10 *
b111100111111010 "
b111 )
b1000 (
b11101 '
b111 %
b1101010110110 D
b10 C
b11011 B
b110 @
b1011011010001100001101010110110 #
b1011011010001100001101010110110 ?
b1011011010001100001101010110110 $
1!
#188000
b10111110100110011000001101111101 $
0!
#189000
b11 *
b11101110010111110000111111011100 $
1!
#190000
b11000011011000010101011110000110 $
0!
#191000
b0 *
b10111100000000111111111101111000 $
1!
#192000
b10111111010110101001101101111110 $
0!
#193000
b1 *
b11001 &
bx $
1!
#194000
b1100111110000111011011011001111 $
0!
#195000
b10 *
b1101010110110 "
b110 )
b11011 '
b10 %
b10101101111001 D
b101 C
b11100 B
b11101 A
b101 @
b10111100111011010010101101111001 #
b10111100111011010010101101111001 ?
b10111100111011010010101101111001 $
1!
#196000
b1111101001010001110010011111010 $
0!
#197000
b11 *
b110000101111001110111001100001 $
1!
#198000
b10001011100101000000100100010111 $
0!
#199000
b0 *
b1010000111101010111100010100001 $
1!
#200000
b11000011011101111001000110000110 $
0!
#201000
b1 *
b11010 &
bx $
1!
#202000
b11111010100011000101100111110101 $
0!
#203000
b10 *
b10101101111001 "
b101 )
b11101 (
b11100 '
b101 %
b100000110101 D
b0 C
b11010 B
b10110 A
b100 @
b11010101101001000100000110101 #
b11010101101001000100000110101 ?
b11010101101001000100000110101 $
1!
#204000
b10100100110101000101000101001 $
0!
#205000
b11 *
b11100000101100010111010111000001 $
1!
#206000
b1100010111001010111010011000101 $
0!
#207000
b0 *
b1001100000000011011010010011000 $
1!
#208000
b10100101101100100111101101001011 $
0!
#209000
b1 *
b11011 &
bx $
1!
#210000
b1110110001000101110011011101100 $
0!
#211000
b10 *
b100000110101 "
b100 )
b10110 (
b11010 '
b0 %
b1011010001010 D
b10 C
b101 B
b1010 A
b0 @
b1000101010100000001011010001010 #
b1000101010100000001011010001010 ?
b1000101010100000001011010001010 $
1!
#212000
b10100111010110001101000101001110 $
0!
#213000
b11 *
b1010100010010111000000010101000 $
1!
#214000
b11010100100111101111110110101001 $
0!
#215000
b0 *
b1010000110010101000110010100001 $
1!
#216000
b10000111000010111011100100001110 $
0!
#217000
b1 *
b11100 &
bx $
1!
#218000
b1001111110101101100000010011111 $
0!
#219000
b10 *
b1011010001010 "
b0 )
b1010 (
b101 '
b10 %
b11010100101010 D
b100 C
b10101 B
b101 A
b111 @
b10010101001011111011010100101010 #
b10010101001011111011010100101010 ?
b10010101001011111011010100101010 $
1!
#220000
b10010101010110100001110100101010 $
0!
#221000
b11 *
b1000110101101011111010010001101 $
1!
#222000
b11001111011101011111111110011110 $
0!
#223000
b0 *
b11100011011011110011000111000 $
1!
#224000
b111100110011111010100001111001 $
0!
#225000
b1 *
b11101 &
bx $
1!
#226000
b11100101001000110100010111001010 $
0!
#227000
b10 *
b11010100101010 "
b111 )
b101 (
b10101 '
b100 %
b100000100010011 D
b1001 B
b11111 A
b10001001111111110100000100010011 #
b10001001111111110100000100010011 ?
b10001001111111110100000100010011 $
1!
#228000
b10110101101000001100100101101011 $
0!
#229000
b11 *
b1100011101101111010111011000111 $
1!
#230000
b11011011000010111101110110110110 $
0!
#231000
b0 *
b11011101000001011001110110111010 $
1!
#232000
b11100010000101101010101111000100 $
0!
#233000
b1 *
b11110 &
bx $
1!
#234000
b11001001001011111101001110010010 $
0!
#235000
b10 *
b100000100010011 "
b11111 (
b1001 '
b1101010110100 D
b10 C
b11010 B
b100 A
b110 @
b1011010001001101001101010110100 #
b1011010001001101001101010110100 ?
b1011010001001101001101010110100 $
1!
#236000
b10111111101110110011101101111111 $
0!
#237000
b11 *
b1000011001100111001000010000110 $
1!
#238000
b11111101011011011111010111111010 $
0!
#239000
b0 *
b1111001001001111001010011110010 $
1!
#240000
b10011001010001010010000100110010 $
0!
#241000
b1 *
b11111 &
bx $
1!
#242000
b11000010010011111100110110000100 $
0!
#243000
b10 *
b1101010110100 "
b110 )
b100 (
b11010 '
b10 %
b10010011100100 D
b11 C
b10010 B
b1001 A
b1 @
b1110010010010011010010011100100 #
b1110010010010011010010011100100 ?
b1110010010010011010010011100100 $
1!
#244000
b11100101010000111100111111001010 $
0!
#245000
b11 *
b11010100101010000111100110101001 $
1!
#246000
b1010000100101011010100010100001 $
0!
#247000
b0 *
b11000111011001011010100110001110 $
1!
#248000
b1111101100010110110101011111011 $
0!
#249000
b1 *
b100000 &
bx $
1!
#250000
b1110111100000101001000011101111 $
0!
#251000
b10 *
b10010011100100 "
b1 )
b1001 (
b10010 '
b11 %
b11110111001001 D
b111 C
b100 B
b11001 A
b0 @
b11100100110010000011110111001001 #
b11100100110010000011110111001001 ?
b11100100110010000011110111001001 $
1!
#252000
b10011011011000001110010100110110 $
0!
#253000
b11 *
b111010101100010100100001110101 $
1!
#254000
b1000111111010000101011010001111 $
0!
#255000
b0 *
b10110101110011011011111101101011 $
1!
#256000
b11000100011001011110011110001000 $
0!
#257000
b1 *
b100001 &
bx $
1!
#258000
b11001101111100111000000110011011 $
0!
#259000
b10 *
b11110111001001 "
b0 )
b11001 (
b100 '
b111 %
b100010110010010 D
b110 C
b1001 B
b111 A
b110 @
b11001001001111100100010110010010 #
b11001001001111100100010110010010 ?
b11001001001111100100010110010010 $
1!
#260000
b10010100010001001101111100101000 $
0!
#261000
b11 *
b10110100001001110000000101101 $
1!
#262000
b10100101101101110101111101001011 $
0!
#263000
b0 *
b1100001011010011011000011000010 $
1!
#264000
b1111000111001111011000011110 $
0!
#265000
b1 *
b100010 &
bx $
1!
#266000
b11110110011110011111110111101100 $
0!
#267000
b10 *
b100010110010010 "
b110 )
b111 (
b1001 '
b110 %
b1110100011000 D
b100 C
b1100 B
b0 A
b11 @
b10001100000000111001110100011000 #
b10001100000000111001110100011000 ?
b10001100000000111001110100011000 $
1!
#268000
b11101000101011100001101111010001 $
0!
#269000
b11 *
b1000011011101100001110010000110 $
1!
#270000
b100000110000000010010001000001 $
0!
#271000
b0 *
b11101101111110110010000111011 $
1!
#272000
b11101100010001001111100111011000 $
0!
#273000
b1 *
b100011 &
bx $
1!
#274000
b101011000110010110001001010110 $
0!
#275000
b10 *
b1110100011000 "
b11 )
b0 (
b1100 '
b100 %
b10001001011011 D
b1 C
b1101 B
b10101 A
b100 @
b101101101011000010001001011011 #
b101101101011000010001001011011 ?
b101101101011000010001001011011 $
1!
#276000
b1110001011001101111101011100010 $
0!
#277000
b11 *
b10011100111110001000000100 $
1!
#278000
b10111001101011000000001101110011 $
0!
#279000
b0 *
b1101100010100001011010011011000 $
1!
#280000
b10001001001111100100110100010010 $
0!
#281000
b1 *
b100100 &
bx $
1!
#282000
b11100100000010001001000111001 $
0!
#283000
b10 *
b10001001011011 "
b100 )
b10101 (
b1101 '
b1 %
b11011011100101 D
b11 C
b10010 B
b10000 A
b111 @
b1110010100001111011011011100101 #
b1110010100001111011011011100101 ?
b1110010100001111011011011100101 $
1!
#284000
b1010000110001011101110010100001 $
0!
#285000
b11 *
b10010101100010010000111100101011 $
1!
#286000
b11000000100100000101110110000001 $
0!
#287000
b0 *
b11100100000110111000010111001000 $
1!
#288000
b10010011101101010101010100100111 $
0!
#289000
b1 *
b100101 &
bx $
1!
#290000
b1111100011000110111000011111 $
0!
#291000
b10 *
b11011011100101 "
b111 )
b10000 (
b10010 '
b11 %
b11101000000100 D
b0 C
b10 B
b100 A
b10 @
b10001000100011101000000100 #
b10001000100011101000000100 ?
b10001000100011101000000100 $
1!
#292000
b10101100001011010010001101011000 $
0!
#293000
b11 *
b1001011010111001000000010010110 $
1!
#294000
b10001010011011101001001100010100 $
0!
#295000
b0 *
b1001000110011011010000010010 $
1!
#296000
b1001011001000100111000010010110 $
0!
#297000
b1 *
b100110 &
bx $
1!
#298000
b10101010110000101101010101010101 $
0!
#299000
b10 *
b11101000000100 "
b10 )
b100 (
b10 '
b0 %
b111011101101 D
b11 C
b10110 B
b11000 A
b11 @
b1110110110000111000111011101101 #
b1110110110000111000111011101101 ?
b1110110110000111000111011101101 $
1!
#300000
b10010101100010110010101100101011 $
0!
#301000
b11 *
b11111010101100010001101111110101 $
1!
#302000
b11010110101101000000001110101101 $
0!
#303000
b0 *
b10011110000010010001000100111 $
1!
#304000
b11000010010010011111111110000100 $
0!
#305000
b1 *
b100111 &
bx $
1!
#306000
b1110011110101111010011011100111 $
0!
#307000
b10 *
b111011101101 "
b11 )
b11000 (
b10110 '
b11 %
b1000010111001 D
b10 C
b11100 B
b11101 A
b111 @
b1011100111011111001000010111001 #
b1011100111011111001000010111001 ?
b1011100111011111001000010111001 $
1!
#308000
b100100110110100101011001001001 $
0!
#309000
b11 *
b11101101111001011011101111011011 $
1!
#310000
b11100100101110100000111111001001 $
0!
#311000
b0 *
b10101000100000111011000101010001 $
1!
#312000
b1010000101111000101111010100001 $
0!
#313000
b1 *
b101000 &
bx $
1!
#314000
b11111101001010100100010111111010 $
0!
#315000
b10 *
b1000010111001 "
b111 )
b11101 (
b11100 '
b10 %
b10000001000101 D
b1 C
b10 B
b11100 A
b110 @
b100010111001100010000001000101 #
b100010111001100010000001000101 ?
b100010111001100010000001000101 $
1!
#316000
b11000001101000010000010110000011 $
0!
#317000
b11 *
b111110011101010100001001111100 $
1!
#318000
b111001010001100001010001110010 $
0!
#319000
b0 *
b1111111010011110011110011111110 $
1!
#320000
b110100010101011111001001101000 $
0!
#321000
b1 *
b101001 &
bx $
1!
#322000
b11000011010001100000110110000110 $
0!
